nupmy/__init__.py
nupmy/__main__.py
nupmy/a.py
nupmy/b.py
nupmy/data/data.txt
nupmy/data/nupmy/DecisionTree/ClassificationTree/classification/__init__.py
nupmy/data/nupmy/DecisionTree/ClassificationTree/classification/diabetes.py
nupmy/data/nupmy/DecisionTree/ClassificationTree/data/diabetes.csv
nupmy/data/nupmy/DecisionTree/ClassificationTree/images/tree.png
nupmy/data/nupmy/DecisionTree/RegressionTree/data/housing.csv
nupmy/data/nupmy/DecisionTree/RegressionTree/regression/housing.py
nupmy/data/nupmy/DecisionTree/RegressionTree/regression/housingRandomForest.py
nupmy/data/nupmy/FML_1/evaluation.py
nupmy/data/nupmy/FML_1/houses_multivariate.py
nupmy/data/nupmy/FML_1/houses_polynomial.py
nupmy/data/nupmy/FML_1/houses_polynomial_house.py
nupmy/data/nupmy/FML_1/houses_univariate.py
nupmy/data/nupmy/FML_1/houses_univariate_animation.py
nupmy/data/nupmy/FML_1/linear_regression.py
nupmy/data/nupmy/FML_1/utilities.py
nupmy/data/nupmy/FML_1/datasets/Position_Salaries.csv
nupmy/data/nupmy/FML_1/datasets/Position_Salaries_base.csv
nupmy/data/nupmy/FML_1/datasets/houses.csv
nupmy/data/nupmy/FML_1/datasets/houses_portaland_simple.csv
nupmy/data/nupmy/FML_2/houses_multivariate.py
nupmy/data/nupmy/FML_2/houses_univariate.py
nupmy/data/nupmy/FML_2/houses_univariate_animation.py
nupmy/data/nupmy/FML_2/linear_regression.py
nupmy/data/nupmy/FML_2/utilities.py
nupmy/data/nupmy/FML_2/datasets/Position_Salaries.csv
nupmy/data/nupmy/FML_2/datasets/Position_Salaries_base.csv
nupmy/data/nupmy/FML_2/datasets/evaluation.py
nupmy/data/nupmy/FML_2/datasets/houses.csv
nupmy/data/nupmy/FML_2/datasets/houses_portaland_simple.csv
nupmy/data/nupmy/FML_3/Code/Diabetes.py
nupmy/data/nupmy/FML_3/Code/logistic_regression.py
nupmy/data/nupmy/FML_3/Code/datasets/Wine.csv
nupmy/data/nupmy/FML_3/Code/datasets/diabetes.csv
nupmy/data/nupmy/FML_4/Sklearn_Base.py
nupmy/data/nupmy/FML_4/Sklearn_Grid.py
nupmy/data/nupmy/FML_4/Sklearn_Pipeline_Grid.py
nupmy/data/nupmy/FML_4/sklearn_Pipeline_Outlier.py
nupmy-1.0.dist-info/METADATA
nupmy-1.0.dist-info/WHEEL
nupmy-1.0.dist-info/top_level.txt
nupmy-1.0.dist-info/RECORD
