Metadata-Version: 2.1
Name: nupmy
Version: 1.0
Summary: simplest example in the python world
License: MIT
